spkcspider/__init__.py
spkcspider/apps/spider/__init__.py
spkcspider/apps/spider/abstract_models/__init__.py
spkcspider/apps/spider/abstract_models/contents.py
spkcspider/apps/spider/abstract_models/info.py
spkcspider/apps/spider/abstract_models/misc.py
spkcspider/apps/spider/admin.py
spkcspider/apps/spider/apps.py
spkcspider/apps/spider/auth.py
spkcspider/apps/spider/conf.py
spkcspider/apps/spider/context_processors.py
spkcspider/apps/spider/fields.py
spkcspider/apps/spider/forms/__init__.py
spkcspider/apps/spider/forms/_auth.py
spkcspider/apps/spider/forms/_contents.py
spkcspider/apps/spider/forms/_core.py
spkcspider/apps/spider/forms/_messages.py
spkcspider/apps/spider/forms/base.py
spkcspider/apps/spider/forms/flatpages.py
spkcspider/apps/spider/functions.py
spkcspider/apps/spider/locale/de/LC_MESSAGES/django.po
spkcspider/apps/spider/management/commands/fix_jsonfields.py
spkcspider/apps/spider/management/commands/revoke_auth_tokens.py
spkcspider/apps/spider/management/commands/update_dynamic_content.py
spkcspider/apps/spider/middleware.py
spkcspider/apps/spider/migrations/0001_initial.py
spkcspider/apps/spider/migrations/0002_20190518_squashed.py
spkcspider/apps/spider/migrations/0003_auto_20190621_1954.py
spkcspider/apps/spider/migrations/0004_auto_20190621_2126.py
spkcspider/apps/spider/migrations/0005_auto_20190626_1620.py
spkcspider/apps/spider/migrations/0006_auto_20190817_1814.py
spkcspider/apps/spider/migrations/0007_auto_20190817_1814.py
spkcspider/apps/spider/migrations/0008_auto_20190817_1815.py
spkcspider/apps/spider/migrations/0009_auto_20190929_2117.py
spkcspider/apps/spider/migrations/0010_auto_20191230_1300.py
spkcspider/apps/spider/migrations/0011_auto_20191230_1305.py
spkcspider/apps/spider/migrations/0012_auto_20191230_1305.py
spkcspider/apps/spider/migrations/0013_auto_20200118_1447.py
spkcspider/apps/spider/migrations/0014_authtoken_attached_to_content.py
spkcspider/apps/spider/migrations/0015_auto_20200119_0750.py
spkcspider-0.29.4.dist-info/LICENSE
spkcspider-0.29.4.dist-info/WHEEL
spkcspider-0.29.4.dist-info/METADATA
spkcspider-0.29.4.dist-info/RECORD
