Metadata-Version: 2.1
Name: spkcspider
Version: 0.29.4
Summary: A secure, decentral platform for maintaining your online identity
Home-page: https://spkcspider.net
License: MIT
Keywords: online identity,decentral networks
Author: Alexander Kaftan
Requires-Python: >=3.6
Classifier: Development Status :: 4 - Beta
Classifier: Framework :: Django
Classifier: Intended Audience :: Developers
Classifier: Intended Audience :: System Administrators
Classifier: License :: OSI Approved :: MIT License
Classifier: Operating System :: POSIX
Classifier: Programming Language :: Python :: 3
Classifier: Programming Language :: Python :: 3.6
Classifier: Programming Language :: Python :: 3.7
Classifier: Programming Language :: Python :: 3.8
Classifier: Topic :: Internet :: WWW/HTTP :: Dynamic Content
Classifier: Topic :: Internet :: WWW/HTTP :: Dynamic Content :: Content Management System
Classifier: Topic :: Internet :: WWW/HTTP :: WSGI :: Application
Provides-Extra: fastcgi
Provides-Extra: mysql
Provides-Extra: postgresql
Provides-Extra: tasks
Provides-Extra: test
Requires-Dist: WSGIProxy2; extra == "test"
Requires-Dist: bleach
Requires-Dist: celery; extra == "tasks" or extra == "test"
Requires-Dist: certifi
Requires-Dist: cryptography
Requires-Dist: django (>=3.0)
Requires-Dist: django-fast-ratelimit
Requires-Dist: django-mysql; extra == "mysql"
Requires-Dist: django-next-prev
Requires-Dist: django-ranged-response
Requires-Dist: django-simple-captcha; extra == "test"
Requires-Dist: django-simple-jsonfield (>=0.3)
Requires-Dist: django-webtest; extra == "test"
Requires-Dist: django-widget-tweaks
Requires-Dist: flipflop; extra == "fastcgi"
Requires-Dist: html5lib
Requires-Dist: mysqlclient; extra == "mysql"
Requires-Dist: psycopg2; extra == "postgresql"
Requires-Dist: rdflib
Requires-Dist: requests
Requires-Dist: spkcspider-domainauth (>=0.4); extra == "test"
Requires-Dist: sqlalchemy; extra == "tasks" or extra == "test"
Project-URL: Repository, https://github.com/spkcspider/spkcspider
